LED_Analyze/__init__.py
LED_Analyze/analysis_main.py
LED_Analyze/db.py
LED_Analyze/gui_calc.py
LED_Analyze/gui_common.py
LED_Analyze/gui_input_select.py
LED_Analyze/gui_input_template.py
LED_Analyze/gui_main.py
LED_Analyze/gui_output.py
LED_Analyze/main.py
LED_Analyze/calc/__init__.py
LED_Analyze/calc/calc_basic.py
LED_Analyze/calc/calc_common.py
LED_Analyze/calc/calc_led.py
ledanalyze-1.0.4.dist-info/METADATA
ledanalyze-1.0.4.dist-info/RECORD
ledanalyze-1.0.4.dist-info/WHEEL
ledanalyze-1.0.4.dist-info/top_level.txt
