Metadata-Version: 2.1
Name: ledanalyze
Version: 1.0.4
Summary: Process colorimetry data
Home-page: https://github.com/pougivan/LED_Analyze
Author: pougivan
Author-email: UNKNOWN
License: UNKNOWN
Platform: UNKNOWN
Classifier: Programming Language :: Python :: 3
Classifier: License :: OSI Approved :: MIT License
Requires-Dist: numpy
Requires-Dist: matplotlib
Requires-Dist: openpyxl
